odoo10_addon_l10n_it_website_portal_fiscalcode-10.0.1.0.0.99.dev5-py3.8-nspkg.pth
odoo/addons/l10n_it_website_portal_fiscalcode/README.rst
odoo/addons/l10n_it_website_portal_fiscalcode/__init__.py
odoo/addons/l10n_it_website_portal_fiscalcode/__manifest__.py
odoo/addons/l10n_it_website_portal_fiscalcode/controllers/__init__.py
odoo/addons/l10n_it_website_portal_fiscalcode/controllers/main.py
odoo/addons/l10n_it_website_portal_fiscalcode/i18n/it.po
odoo/addons/l10n_it_website_portal_fiscalcode/i18n/l10n_it_website_portal_fiscalcode.pot
odoo/addons/l10n_it_website_portal_fiscalcode/readme/DESCRIPTION.rst
odoo/addons/l10n_it_website_portal_fiscalcode/static/description/icon.png
odoo/addons/l10n_it_website_portal_fiscalcode/static/description/index.html
odoo/addons/l10n_it_website_portal_fiscalcode/views/l10n_it_website_portal_fiscalcode_templates.xml
odoo10_addon_l10n_it_website_portal_fiscalcode-10.0.1.0.0.99.dev5.dist-info/METADATA
odoo10_addon_l10n_it_website_portal_fiscalcode-10.0.1.0.0.99.dev5.dist-info/WHEEL
odoo10_addon_l10n_it_website_portal_fiscalcode-10.0.1.0.0.99.dev5.dist-info/namespace_packages.txt
odoo10_addon_l10n_it_website_portal_fiscalcode-10.0.1.0.0.99.dev5.dist-info/top_level.txt
odoo10_addon_l10n_it_website_portal_fiscalcode-10.0.1.0.0.99.dev5.dist-info/RECORD
